djangocms_device_mockups/__init__.py
djangocms_device_mockups/apps.py
djangocms_device_mockups/cms_plugins.py
djangocms_device_mockups/consts.py
djangocms_device_mockups/forms.py
djangocms_device_mockups/models.py
djangocms_device_mockups/tests.py
djangocms_device_mockups/migrations/0001_initial.py
djangocms_device_mockups/migrations/__init__.py
djangocms_device_mockups/static/djangocms_device_mockups/css/device-mockups.css
djangocms_device_mockups/static/djangocms_device_mockups/css/device-mockups.css.map
djangocms_device_mockups/static/djangocms_device_mockups/css/device-mockups.min.css
djangocms_device_mockups/static/djangocms_device_mockups/device-mockups/Chromebook/portrait_black.png
djangocms_device_mockups/static/djangocms_device_mockups/device-mockups/HtcOneM8/landscape_black.png
djangocms_device_mockups/static/djangocms_device_mockups/device-mockups/HtcOneM8/portrait_black.png
djangocms_device_mockups/static/djangocms_device_mockups/device-mockups/HuaweiP8/landscape_gold.png
djangocms_device_mockups/static/djangocms_device_mockups/device-mockups/HuaweiP8/portrait_gold.png
djangocms_device_mockups/static/djangocms_device_mockups/device-mockups/Lumia930/landscape_black.png
djangocms_device_mockups/static/djangocms_device_mockups/device-mockups/Lumia930/landscape_white.png
djangocms_device_mockups/static/djangocms_device_mockups/device-mockups/Lumia930/portrait_black.png
djangocms_device_mockups/static/djangocms_device_mockups/device-mockups/Lumia930/portrait_white.png
djangocms_device_mockups/static/djangocms_device_mockups/device-mockups/Macbook/portrait_black.png
djangocms_device_mockups/static/djangocms_device_mockups/device-mockups/Macbook/portrait_gold.png
djangocms_device_mockups/static/djangocms_device_mockups/device-mockups/Macbook/portrait_white.png
djangocms_device_mockups/static/djangocms_device_mockups/device-mockups/Macbook2015/portrait_black.png
djangocms_device_mockups-1.0.1.dist-info/METADATA
djangocms_device_mockups-1.0.1.dist-info/WHEEL
djangocms_device_mockups-1.0.1.dist-info/top_level.txt
djangocms_device_mockups-1.0.1.dist-info/RECORD
